llama_index/readers/github/__init__.py
llama_index/readers/github/collaborators/__init__.py
llama_index/readers/github/collaborators/base.py
llama_index/readers/github/collaborators/github_client.py
llama_index/readers/github/issues/__init__.py
llama_index/readers/github/issues/base.py
llama_index/readers/github/issues/github_client.py
llama_index/readers/github/repository/__init__.py
llama_index/readers/github/repository/base.py
llama_index/readers/github/repository/github_client.py
llama_index/readers/github/repository/utils.py
flying_delta_readers_github-0.1.0.dist-info/METADATA
flying_delta_readers_github-0.1.0.dist-info/WHEEL
flying_delta_readers_github-0.1.0.dist-info/RECORD
